{
  "users": [
    {
      "uid": 0,
      "userName": "张0",
      "detail": "address0"
    },
    {
      "uid": 1,
      "userName": "张1",
      "detail": "address1"
    },
    {
      "uid": 2,
      "userName": "张2",
      "detail": "address2"
    },
    {
      "uid": 3,
      "userName": "张3",
      "detail": "address3"
    },
    {
      "uid": 4,
      "userName": "张4",
      "detail": "address4"
    },
    {
      "uid": 5,
      "userName": "张5",
      "detail": "address5"
    },
    {
      "uid": 6,
      "userName": "张6",
      "detail": "address6"
    },
    {
      "uid": 7,
      "userName": "张7",
      "detail": "address7"
    },
    {
      "uid": 8,
      "userName": "张8",
      "detail": "address8"
    },
    {
      "uid": 9,
      "userName": "张9",
      "detail": "address9"
    },
    {
      "uid": 10,
      "userName": "spring",
      "detail": "708"
    }
  ]
}